{
 "accept_payment": 0,
 "allow_comments": 1,
 "allow_delete": 0,
 "allow_edit": 1,
 "allow_incomplete": 1,
 "allow_multiple": 1,
 "allow_print": 0,
 "amount": 0.0,
 "amount_based_on_field": 0,
 "apply_document_permissions": 0,
 "button_label": "Submit Request",
 "creation": "2025-01-20 10:00:00.000000",
 "currency": "USD",
 "doc_type": "Variation Order",
 "docstatus": 0,
 "doctype": "Web Form",
 "idx": 0,
 "introduction_text": "Submit a variation order request for your project. All requests will be reviewed by the project team.",
 "is_standard": 1,
 "login_required": 1,
 "max_attachment_size": 5,
 "modified": "2025-01-20 10:00:00.000000",
 "modified_by": "Administrator",
 "module": "Quantity Surveying",
 "name": "Variation Order Request",
 "owner": "Administrator",
 "payment_button_label": "Buy Now",
 "print_format": "",
 "published": 1,
 "route": "variation-order-request",
 "show_attachments": 1,
 "show_list": 0,
 "show_sidebar": 1,
 "success_message": "Your variation order request has been submitted successfully. You will be contacted for further details.",
 "success_title": "Request Submitted",
 "title": "Variation Order Request",
 "web_form_fields": [
  {
   "allow_read_on_all_link_options": 0,
   "fieldname": "project",
   "fieldtype": "Link",
   "hidden": 0,
   "label": "Project",
   "max_length": 0,
   "max_value": 0,
   "options": "Project",
   "read_only": 0,
   "reqd": 1,
   "show_in_filter": 0
  },
  {
   "allow_read_on_all_link_options": 0,
   "fieldname": "variation_type",
   "fieldtype": "Select",
   "hidden": 0,
   "label": "Variation Type",
   "max_length": 0,
   "max_value": 0,
   "options": "Addition\\nOmission\\nSubstitution",
   "read_only": 0,
   "reqd": 1,
   "show_in_filter": 0
  },
  {
   "allow_read_on_all_link_options": 0,
   "fieldname": "description",
   "fieldtype": "Text",
   "hidden": 0,
   "label": "Description",
   "max_length": 1000,
   "max_value": 0,
   "read_only": 0,
   "reqd": 1,
   "show_in_filter": 0
  },
  {
   "allow_read_on_all_link_options": 0,
   "fieldname": "reason",
   "fieldtype": "Text",
   "hidden": 0,
   "label": "Reason for Variation",
   "max_length": 500,
   "max_value": 0,
   "read_only": 0,
   "reqd": 1,
   "show_in_filter": 0
  }
 ]
}
